azure/cli/__main__.py
azure/cli/command_modules/__init__.py
azure/cli/command_modules/acr/__init__.py
azure/cli/command_modules/acr/_agentpool_polling.py
azure/cli/command_modules/acr/_archive_utils.py
azure/cli/command_modules/acr/_azure_utils.py
azure/cli/command_modules/acr/_client_factory.py
azure/cli/command_modules/acr/_constants.py
azure/cli/command_modules/acr/_docker_utils.py
azure/cli/command_modules/acr/_errors.py
azure/cli/command_modules/acr/_format.py
azure/cli/command_modules/acr/_help.py
azure/cli/command_modules/acr/_params.py
azure/cli/command_modules/acr/_run_polling.py
azure/cli/command_modules/acr/_stream_utils.py
azure/cli/command_modules/acr/_utils.py
azure/cli/command_modules/acr/_validators.py
azure/cli/command_modules/acr/agentpool.py
azure/cli/command_modules/acr/build.py
azure/cli/command_modules/acr/check_health.py
azure/cli/command_modules/acr/commands.py
azure/cli/command_modules/acr/connected_registry.py
azure/cli/command_modules/acr/credential.py
azure/cli/command_modules/acr/custom.py
azure/cli/command_modules/acr/helm.py
azure/cli/command_modules/acr/import.py
azure/cli/command_modules/acr/manifest.py
azure/cli/command_modules/acr/network_rule.py
azure/cli/command_modules/acr/notary.py
azure/cli/command_modules/acr/pack.py
azure/cli/command_modules/acr/policy.py
azure/cli/command_modules/acr/private_endpoint_connection.py
azure/cli/command_modules/acr/replication.py
azure/cli/command_modules/acr/repository.py
azure/cli/command_modules/acr/run.py
azure/cli/command_modules/acr/scope_map.py
azure/cli/command_modules/acr/task.py
azure/cli/command_modules/acr/taskrun.py
azure/cli/command_modules/acr/token.py
azure/cli/command_modules/acr/webhook.py
azure/cli/command_modules/acs/__init__.py
azure/cli/command_modules/acs/_client_factory.py
azure/cli/command_modules/acs/_completers.py
azure/cli/command_modules/acs/_consts.py
azure/cli/command_modules/acs/_format.py
azure/cli/command_modules/acs/_graph.py
azure_cli-2.44.1.dist-info/LICENSE.txt
azure_cli-2.44.1.dist-info/METADATA
azure_cli-2.44.1.dist-info/WHEEL
azure_cli-2.44.1.dist-info/top_level.txt
azure_cli-2.44.1.dist-info/RECORD
