Metadata-Version: 2.1
Name: azure-cli
Version: 2.44.1
Summary: Microsoft Azure Command-Line Tools
Home-page: https://github.com/Azure/azure-cli
Author: Microsoft Corporation
Author-email: azpycli@microsoft.com
License: MIT
Classifier: Development Status :: 5 - Production/Stable
Classifier: Intended Audience :: Developers
Classifier: Intended Audience :: System Administrators
Classifier: Programming Language :: Python
Classifier: Programming Language :: Python :: 3
Classifier: Programming Language :: Python :: 3.7
Classifier: Programming Language :: Python :: 3.8
Classifier: Programming Language :: Python :: 3.9
Classifier: Programming Language :: Python :: 3.10
Classifier: License :: OSI Approved :: MIT License
Requires-Python: >=3.7.0
License-File: LICENSE.txt
Requires-Dist: antlr4-python3-runtime (~=4.9.3)
Requires-Dist: azure-appconfiguration (~=1.1.1)
Requires-Dist: azure-batch (~=13.0.0)
Requires-Dist: azure-cli-core (==2.44.1)
Requires-Dist: azure-cosmos (>=3.0.2,~=3.0)
Requires-Dist: azure-data-tables (==12.4.0)
Requires-Dist: azure-datalake-store (~=0.0.49)
Requires-Dist: azure-graphrbac (~=0.60.0)
Requires-Dist: azure-keyvault-administration (==4.0.0b3)
Requires-Dist: azure-keyvault-keys (==4.8.0b2)
Requires-Dist: azure-keyvault (~=1.1.0)
Requires-Dist: azure-loganalytics (~=0.1.0)
Requires-Dist: azure-mgmt-advisor (==9.0.0)
Requires-Dist: azure-mgmt-apimanagement (~=3.0.0)
Requires-Dist: azure-mgmt-appconfiguration (==2.2.0)
Requires-Dist: azure-mgmt-applicationinsights (~=1.0.0)
Requires-Dist: azure-mgmt-authorization (~=0.61.0)
Requires-Dist: azure-mgmt-batchai (==7.0.0b1)
Requires-Dist: azure-mgmt-batch (~=17.0.0)
Requires-Dist: azure-mgmt-billing (==6.0.0)
Requires-Dist: azure-mgmt-botservice (~=2.0.0b3)
Requires-Dist: azure-mgmt-cdn (==12.0.0)
Requires-Dist: azure-mgmt-cognitiveservices (~=13.3.0)
Requires-Dist: azure-mgmt-compute (~=29.0.0)
Requires-Dist: azure-mgmt-consumption (~=2.0)
Requires-Dist: azure-mgmt-containerinstance (~=9.1.0)
Requires-Dist: azure-mgmt-containerregistry (==10.0.0)
Requires-Dist: azure-mgmt-containerservice (~=21.1.0)
Requires-Dist: azure-mgmt-cosmosdb (==8.0.0)
Requires-Dist: azure-mgmt-databoxedge (~=1.0.0)
Requires-Dist: azure-mgmt-datalake-analytics (~=0.2.1)
Requires-Dist: azure-mgmt-datalake-store (~=0.5.0)
Requires-Dist: azure-mgmt-datamigration (~=10.0.0)
Requires-Dist: azure-mgmt-deploymentmanager (~=0.2.0)
Requires-Dist: azure-mgmt-devtestlabs (~=4.0)
Requires-Dist: azure-mgmt-dns (~=8.0.0)
Requires-Dist: azure-mgmt-eventgrid (==10.2.0b2)
Requires-Dist: azure-mgmt-eventhub (~=10.1.0)
Requires-Dist: azure-mgmt-extendedlocation (==1.0.0b2)
Requires-Dist: azure-mgmt-hdinsight (~=9.0.0)
Requires-Dist: azure-mgmt-imagebuilder (~=1.1.0)
Requires-Dist: azure-mgmt-iotcentral (~=10.0.0b1)
Requires-Dist: azure-mgmt-iothub (==2.3.0)
Requires-Dist: azure-mgmt-iothubprovisioningservices (==1.1.0)
Requires-Dist: azure-mgmt-keyvault (==10.1.0)
Requires-Dist: azure-mgmt-kusto (~=0.3.0)
Requires-Dist: azure-mgmt-loganalytics (==13.0.0b4)
Requires-Dist: azure-mgmt-managedservices (~=1.0)
Requires-Dist: azure-mgmt-managementgroups (~=1.0.0)
Requires-Dist: azure-mgmt-maps (~=2.0.0)
Requires-Dist: azure-mgmt-marketplaceordering (==1.1.0)
Requires-Dist: azure-mgmt-media (~=9.0)
Requires-Dist: azure-mgmt-monitor (~=5.0.0)
Requires-Dist: azure-mgmt-msi (~=6.1.0)
Requires-Dist: azure-mgmt-netapp (~=9.0.1)
Requires-Dist: azure-mgmt-network (~=21.0.1)
Requires-Dist: azure-mgmt-policyinsights (~=1.1.0b2)
Requires-Dist: azure-mgmt-privatedns (~=1.0.0)
Requires-Dist: azure-mgmt-rdbms (~=10.2.0b5)
Requires-Dist: azure-mgmt-recoveryservicesbackup (~=5.1.0b1)
Requires-Dist: azure-mgmt-recoveryservices (~=2.1.0)
Requires-Dist: azure-mgmt-redhatopenshift (==1.1.0)
Requires-Dist: azure-mgmt-redis (~=14.1.0)
Requires-Dist: azure-mgmt-relay (~=0.1.0)
Requires-Dist: azure-mgmt-resource (==21.1.0b1)
Requires-Dist: azure-mgmt-search (~=8.0)
Requires-Dist: azure-mgmt-security (==3.0.0)
Requires-Dist: azure-mgmt-servicebus (~=8.1.0)
Requires-Dist: azure-mgmt-servicefabricmanagedclusters (~=1.0.0)
Requires-Dist: azure-mgmt-servicelinker (==1.2.0b1)
Requires-Dist: azure-mgmt-servicefabric (~=1.0.0)
Requires-Dist: azure-mgmt-signalr (==1.1.0)
Requires-Dist: azure-mgmt-sqlvirtualmachine (==1.0.0b4)
Requires-Dist: azure-mgmt-sql (==4.0.0b6)
Requires-Dist: azure-mgmt-storage (~=21.0.0)
Requires-Dist: azure-mgmt-synapse (==2.1.0b5)
Requires-Dist: azure-mgmt-trafficmanager (~=1.0.0)
Requires-Dist: azure-mgmt-web (==7.0.0)
Requires-Dist: azure-multiapi-storage (~=1.0.0)
Requires-Dist: azure-storage-common (~=1.4)
Requires-Dist: azure-synapse-accesscontrol (~=0.5.0)
Requires-Dist: azure-synapse-artifacts (~=0.14.0)
Requires-Dist: azure-synapse-managedprivateendpoints (~=0.3.0)
Requires-Dist: azure-synapse-spark (~=0.2.0)
Requires-Dist: chardet (~=3.0.4)
Requires-Dist: colorama (~=0.4.4)
Requires-Dist: fabric (~=2.4)
Requires-Dist: javaproperties (~=0.5.1)
Requires-Dist: jsondiff (~=2.0.0)
Requires-Dist: packaging (<22.0,>=20.9)
Requires-Dist: PyGithub (~=1.38)
Requires-Dist: PyMySQL (~=1.0.2)
Requires-Dist: PyNaCl (~=1.5.0)
Requires-Dist: scp (~=0.13.2)
Requires-Dist: semver (==2.13.0)
Requires-Dist: six (>=1.10.0)
Requires-Dist: sshtunnel (~=0.1.4)
Requires-Dist: urllib3[secure]
Requires-Dist: websocket-client (~=1.3.1)
Requires-Dist: xmltodict (~=0.12)
Requires-Dist: distro ; sys_platform == "linux"
